whatif_analyzer/__init__.py
whatif_analyzer/analyzer.py
whatif_analyzer/cli.py
whatif_analyzer/edge_cases.py
whatif_analyzer/report.py
whatif_analyzer/type_inference.py
whatif_analyzer-0.1.0.dist-info/METADATA
whatif_analyzer-0.1.0.dist-info/WHEEL
whatif_analyzer-0.1.0.dist-info/entry_points.txt
whatif_analyzer-0.1.0.dist-info/licenses/LICENSE
whatif_analyzer-0.1.0.dist-info/RECORD
